miner_viz.libs/libstdc++-a9383cce.so.6.0.28
miner_viz.libs/libgcc_s-a04fdf82.so.1
miner_viz-0.0.1.dev0.dist-info/METADATA
miner_viz-0.0.1.dev0.dist-info/RECORD
miner_viz-0.0.1.dev0.dist-info/entry_points.txt
miner_viz-0.0.1.dev0.dist-info/WHEEL
miner_viz/__init__.py
miner_viz/_core.cpython-310-x86_64-linux-gnu.so
miner_viz/__main__.py
